dimredtools_pybind.cp37-win_amd64.pyd
dimredtools/__init__.py
dimredtools/helper.py
dimredtools-0.4.1.dist-info/LICENSE
dimredtools-0.4.1.dist-info/METADATA
dimredtools-0.4.1.dist-info/WHEEL
dimredtools-0.4.1.dist-info/top_level.txt
dimredtools-0.4.1.dist-info/RECORD
